{
    "actions": [
        {
            "id": "switch_off",
            "highlight": true,
            "title": {
                "en": "Switch off",
                "de": "Ausschalten"
            },
            "titleFormatted": {
                "en": "Switch off the player",
                "de": "Player ausschalten"
            },
            "hint": {
                "en": "Use this card to switch off the player",
                "de": "Verwenden Sie diese Karte, um den Player auszuschalten"
            }
        },
        {
            "id": "call_preset",
            "highlight": true,
            "title": {
                "en": "Call preset",
                "de": "Preset aufrufen"
            },
            "titleFormatted": {
                "en": "Call up preset [[preset_number]]",
                "de": "Preset [[preset_number]] aufrufen"
            },
            "hint": {
                "en": "Use this card to call up a preset",
                "de": "Verwenden Sie diese Karte, um einen Preset aufzurufen"
            },
            "args": [
                {
                    "name": "preset_number",
                    "type": "dropdown",
                    "values": [
                        {
                            "id": "1",
                            "label": "1"
                        },
                        {
                            "id": "2",
                            "label": "2"
                        },
                        {
                            "id": "3",
                            "label": "3"
                        },
                        {
                            "id": "4",
                            "label": "4"
                        },
                        {
                            "id": "5",
                            "label": "5"
                        },
                        {
                            "id": "6",
                            "label": "6"
                        },
                        {
                            "id": "7",
                            "label": "7"
                        },
                        {
                            "id": "8",
                            "label": "8"
                        },
                        {
                            "id": "9",
                            "label": "9"
                        },
                        {
                            "id": "10",
                            "label": "10"
                        },
                        {
                            "id": "11",
                            "label": "11"
                        },
                        {
                            "id": "12",
                            "label": "12"
                        }
                    ]
                }
            ]
        }
    ]
}